full_adder.v
module FA(    input a, b, cin,
output cout, sum );

assign cout= (b&cin)|(a&cin)|(a&b);
assign sum =a^b^cin;

endmodule

full_adder_tb.v
module testbench();

reg a,b,cin;
wire cout,sum;

FA fa(a,b,cin,cout,sum);
integer i;
initial
begin
  $dumpfile("full_adder.vcd");
  $dumpvars(0,testbench);
  for(i=0;i<8;i=i+1)
  begin
    {a,b,cin}=i;
    #10
    $display("sum: %b,carry: %b",sum,cout);
  end


end

endmodule

full_adder.vcd
$date
	Sun Dec 31 03:56:44 2023
$end
$version
	Icarus Verilog
$end
$timescale
	1s
$end
$scope module testbench $end
$var wire 1 ! sum $end
$var wire 1 " cout $end
$var reg 1 # a $end
$var reg 1 $ b $end
$var reg 1 % cin $end
$var integer 32 & i [31:0] $end
$scope module fa $end
$var wire 1 # a $end
$var wire 1 $ b $end
$var wire 1 % cin $end
$var wire 1 " cout $end
$var wire 1 ! sum $end
$upscope $end
$upscope $end
$enddefinitions $end
$comment Show the parameter values. $end
$dumpall
$end
#0
$dumpvars
b0 &
0%
0$
0#
0"
0!
$end
#10
1!
1%
b1 &
#20
1!
1$
0%
b10 &
#30
1"
0!
1%
b11 &
#40
0"
1!
1#
0$
0%
b100 &
#50
1"
0!
1%
b101 &
#60
0!
1$
0%
b110 &
#70
1!
1%
b111 &
#80
b1000 &
