thermostat.v


module  thermostat_module(input too_cold,input too_hot,input mode,
input fan_on,output heater,output aircon,output fan);
assign heater = too_cold & mode;
//reg not_mode=!mode
assign aircon = too_hot & (~mode);
assign fan = fan_on | ((~fan_on)&(~mode)&too_hot) | ((~fan_on)&too_cold&mode);





endmodule

thermostat_tb.v
module testbench();
reg too_cold;
reg too_hot;
reg fan_on;
reg mode;
wire fan;
wire heater;
wire aircon;
integer i;
thermostat_module thermostat_module(too_cold,too_hot,mode,fan_on,heater,aircon,fan);

    initial
    begin
        $dumpfile("thermostat.vcd");
        $dumpvars(0,testbench);

        for(i=0;i<16;i=i+1)
        begin
            {mode,too_hot,too_cold,fan_on}=i;
            #10
            $display("heater: ",heater);
            $display("ac: ",aircon);
            $display("fan: ",fan) ;
        end
    end



endmodule

thermostat.vcd
$date
	Sat Dec 30 22:29:10 2023
$end
$version
	Icarus Verilog
$end
$timescale
	1s
$end
$scope module testbench $end
$var wire 1 ! heater $end
$var wire 1 " fan $end
$var wire 1 # aircon $end
$var reg 1 $ fan_on $end
$var reg 1 % mode $end
$var reg 1 & too_cold $end
$var reg 1 ' too_hot $end
$var integer 32 ( i [31:0] $end
$scope module thermostat_module $end
$var wire 1 # aircon $end
$var wire 1 " fan $end
$var wire 1 $ fan_on $end
$var wire 1 ! heater $end
$var wire 1 % mode $end
$var wire 1 & too_cold $end
$var wire 1 ' too_hot $end
$upscope $end
$upscope $end
$enddefinitions $end
$comment Show the parameter values. $end
$dumpall
$end
#0
$dumpvars
b0 (
0'
0&
0%
0$
0#
0"
0!
$end
#10
1"
1$
b1 (
#20
0"
1&
0$
b10 (
#30
1"
1$
b11 (
#40
1"
1#
1'
0&
0$
b100 (
#50
1$
b101 (
#60
1"
1&
0$
b110 (
#70
1$
b111 (
#80
0"
0#
1%
0'
0&
0$
b1000 (
#90
1"
1$
b1001 (
#100
1"
1!
1&
0$
b1010 (
#110
1$
b1011 (
#120
0"
0!
1'
0&
0$
b1100 (
#130
1"
1$
b1101 (
#140
1"
1!
1&
0$
b1110 (
#150
1$
b1111 (
#160
b10000 (
